{
      "typically within": 0,
      "better preserves": 1,
      "sometimes needs": 2,
      "face challenges with": 3,
      "may occur after": 4,
      "extracts": 5,
      "shrink": 6,
      "visualized by": 7,
      "rare complication includes": 8,
      "collaborates with": 9,
      "in children": 10,
      "lacks": 11,
      "prolong": 12,
      "has duration": 13,
      "rehabilitated with": 14,
      "training requirement": 15,
      "aspiration treats": 16,
      "validated by": 17,
      "travel through": 18,
      "has side effects": 19,
      "correlate with": 20,
      "radiopaque stripe confirms": 21,
      "decision based on": 22,
      "combines": 23,
      "vibrates": 24,
      "results": 25,
      "is a type of": 26,
      "warrants": 27,
      "may risk": 28,
      "offers": 29,
      "flags": 30,
      "screened before": 31,
      "dressed with": 32,
      "diseases include": 33,
      "provides better": 34,
      "result": 35,
      "awarded": 36,
      "excreted by": 37,
      "smaller size for": 38,
      "branches from": 39,
      "increases risk of": 40,
      "shielded by": 41,
      "normalizes after": 42,
      "alleviates": 43,
      "samples": 44,
      "investigated for": 45,
      "builds": 46,
      "residual volume checks prevent": 47,
      "higher risk of": 48,
      "encourages": 49,
      "images": 50,
      "measured via": 51,
      "can be managed by": 52,
      "shape": 53,
      "makes": 54,
      "evaluated with": 55,
      "lower": 56,
      "remains gold standard for": 57,
      "targets": 58,
      "contrast-enhanced": 59,
      "presents with": 60,
      "applied in": 61,
      "detects": 62,
      "preferred over": 63,
      "complicates": 64,
      "interpreted with": 65,
      "access site for": 66,
      "has success rate": 67,
      "screened via": 68,
      "developed in": 69,
      "imaging": 70,
      "regulated by": 71,
      "dilates": 72,
      "infantile form often": 73,
      "has revision rate": 74,
      "reimbursed under": 75,
      "achieve": 76,
      "prolongs": 77,
      "performed using": 78,
      "associates with": 79,
      "ethical issues include": 80,
      "shields": 81,
      "common after": 82,
      "study": 83,
      "sometimes required for": 84,
      "equipment includes": 85,
      "can detect": 86,
      "tests for": 87,
      "enlarges": 88,
      "differentiate into": 89,
      "screened in": 90,
      "addresses": 91,
      "blocks": 92,
      "heals within": 93,
      "\u4e0d\u9002\u7528\u4e8e": 94,
      "diagnostic for": 95,
      "faces": 96,
      "decompresses": 97,
      "travel via": 98,
      "build capacity for": 99,
      "transmitted for": 100,
      "helps assess": 101,
      "requires": 102,
      "symptom": 103,
      "not recommended": 104,
      "guide": 105,
      "checked for": 106,
      "staged via": 107,
      "portable version": 108,
      "\u9700\u8981": 109,
      "replace": 110,
      "safe for": 111,
      "enucleation techniques include": 112,
      "insertion requires": 113,
      "unique needs for": 114,
      "must have": 115,
      "advises": 116,
      "are processed by": 117,
      "billed as": 118,
      "restores": 119,
      "develop from": 120,
      "addressed by": 121,
      "clarify": 122,
      "lubricated with": 123,
      "calculated from": 124,
      "enforced in": 125,
      "may prevent": 126,
      "assessed via": 127,
      "can measure": 128,
      "secures": 129,
      "team": 130,
      "indicator of": 131,
      "necessitate": 132,
      "costs": 133,
      "repaired via": 134,
      "beneficial for": 135,
      "diagnosed with": 136,
      "frequently need": 137,
      "have higher risk": 138,
      "classifies as": 139,
      "lichen sclerosus causes": 140,
      "often are": 141,
      "sometimes avoided in": 142,
      "alternative to": 143,
      "potential risk of": 144,
      "preoperative care": 145,
      "bloody output indicates": 146,
      "perfusion imaging": 147,
      "readmission risk": 148,
      "has higher": 149,
      "narrows": 150,
      "better for": 151,
      "sterilized by": 152,
      "evade": 153,
      "modulate": 154,
      "feeding rate adjusted by": 155,
      "comes from": 156,
      "required after": 157,
      "face shortages of": 158,
      "quality measure": 159,
      "performed more in": 160,
      "\u6d89\u53ca": 161,
      "harbors": 162,
      "consults": 163,
      "adjuvant therapy": 164,
      "amplify": 165,
      "mandated in": 166,
      "has alternative": 167,
      "sometimes need": 168,
      "may contribute to": 169,
      "transmitted by": 170,
      "revolutionized": 171,
      "administered during": 172,
      "delayed by": 173,
      "training": 174,
      "automates": 175,
      "has higher cure rate than": 176,
      "oxygenates": 177,
      "reduced in": 178,
      "incised with": 179,
      "preoperative step": 180,
      "cost": 181,
      "risk factor": 182,
      "results from": 183,
      "postoperative care": 184,
      "survivorship issue": 185,
      "superior in": 186,
      "stabilizes": 187,
      "supported by": 188,
      "links": 189,
      "interpreted as": 190,
      "optimizes": 191,
      "formed by": 192,
      "more available than": 193,
      "is made of": 194,
      "required for": 195,
      "accessed by": 196,
      "superior for": 197,
      "pain medication": 198,
      "targeted by": 199,
      "more extensive than": 200,
      "prevalence high in": 201,
      "useful for": 202,
      "diagnoses via": 203,
      "is needed for": 204,
      "requires special care for": 205,
      "timing affects": 206,
      "may benefit from": 207,
      "fall out": 208,
      "caused by": 209,
      "covers": 210,
      "present": 211,
      "employed by": 212,
      "converts": 213,
      "cultured for": 214,
      "check": 215,
      "differentiate": 216,
      "require": 217,
      "regenerates": 218,
      "available for": 219,
      "repeats": 220,
      "family training includes": 221,
      "prevent rejection after": 222,
      "factors into": 223,
      "suction setting varies by": 224,
      "detected via": 225,
      "changes": 226,
      "are used in": 227,
      "does not prevent": 228,
      "costs covered by": 229,
      "exerts": 230,
      "traditional material for": 231,
      "accessed for": 232,
      "measured in": 233,
      "restricted in": 234,
      "respond to": 235,
      "final results": 236,
      "future involves": 237,
      "hemostasis": 238,
      "closes": 239,
      "does not protect": 240,
      "involves": 241,
      "stored with": 242,
      "may result in": 243,
      "discharge criteria": 244,
      "filter": 245,
      "has variant": 246,
      "screen for": 247,
      "erode": 248,
      "research": 249,
      "\u53ef\u80fd\u5f15\u8d77": 250,
      "results in": 251,
      "incises": 252,
      "operates": 253,
      "depend on": 254,
      "risk rejection after": 255,
      "broken down by": 256,
      "helps differentiate": 257,
      "assessed after": 258,
      "can determine": 259,
      "needed in": 260,
      "fitted by": 261,
      "causes risk of": 262,
      "observed through": 263,
      "transitions to": 264,
      "optional in": 265,
      "neutralize": 266,
      "alternatives include": 267,
      "benefits from": 268,
      "increases demand for": 269,
      "carries risk": 270,
      "detected with": 271,
      "confirm": 272,
      "postoperative medication": 273,
      "malignant form associates with": 274,
      "congenital form associates with": 275,
      "breaks down": 276,
      "administered by": 277,
      "secreted by": 278,
      "can be caused by": 279,
      "considered": 280,
      "anesthesia": 281,
      "is reason for": 282,
      "troubleshoots": 283,
      "worn for": 284,
      "indications include": 285,
      "prevalence varies by": 286,
      "safer than": 287,
      "evolved for": 288,
      "constrict during": 289,
      "advised for": 290,
      "excretes": 291,
      "stores": 292,
      "reroutes": 293,
      "heals through": 294,
      "advanced to": 295,
      "postpones": 296,
      "prefer": 297,
      "tailored to": 298,
      "delays": 299,
      "accumulates in": 300,
      "cumulative over": 301,
      "grafts use": 302,
      "trained with": 303,
      "mask": 304,
      "improves after": 305,
      "standardize": 306,
      "released by": 307,
      "subtype of": 308,
      "enable": 309,
      "show": 310,
      "can indicate": 311,
      "operate": 312,
      "improved": 313,
      "can be diagnosed with": 314,
      "postoperative": 315,
      "often taken from": 316,
      "increases risk": 317,
      "lasts": 318,
      "dissolved with": 319,
      "treats": 320,
      "is at risk in": 321,
      "helps diagnose": 322,
      "is a": 323,
      "audited for": 324,
      "has longer": 325,
      "provided by": 326,
      "reconnects": 327,
      "correlates with": 328,
      "long-term outcome": 329,
      "aim to": 330,
      "for large": 331,
      "cuts off blood supply": 332,
      "project to": 333,
      "help in": 334,
      "reduces": 335,
      "repaired by": 336,
      "shows characteristic pattern in": 337,
      "preserve": 338,
      "has age restriction": 339,
      "has contraindication": 340,
      "produce": 341,
      "lead to": 342,
      "occupational hazard for": 343,
      "corrected with": 344,
      "parametric mapping": 345,
      "recommended by": 346,
      "concern": 347,
      "mediated by": 348,
      "explores": 349,
      "is measured by": 350,
      "supplies": 351,
      "releases": 352,
      "obtains": 353,
      "phagocytose": 354,
      "progresses through": 355,
      "increase risk": 356,
      "postoperative care involves": 357,
      "success rate": 358,
      "marks": 359,
      "is complication of": 360,
      "measures for": 361,
      "examined for": 362,
      "can treat": 363,
      "sometimes performed after": 364,
      "are rare": 365,
      "provide": 366,
      "provokes": 367,
      "adjusted via": 368,
      "sometimes combined with": 369,
      "reduces edema after": 370,
      "eliminates": 371,
      "precedes": 372,
      "indicator": 373,
      "has lower": 374,
      "inform": 375,
      "protocol follows": 376,
      "recovery": 377,
      "irrigates": 378,
      "specialist for": 379,
      "custom-fitted for": 380,
      "buccal mucosa grafting has": 381,
      "detected in": 382,
      "reduces risk of": 383,
      "followed up in": 384,
      "stored for": 385,
      "documented with": 386,
      "partial type": 387,
      "in diabetics": 388,
      "less invasive than": 389,
      "realigns": 390,
      "indication": 391,
      "historically common in": 392,
      "assesses risk for": 393,
      "follows": 394,
      "advanced stage of": 395,
      "are a class of": 396,
      "performed before": 397,
      "is used for": 398,
      "eliminated by": 399,
      "fights": 400,
      "does not affect": 401,
      "subsides in": 402,
      "risk": 403,
      "implants": 404,
      "is processed by": 405,
      "often placed during": 406,
      "advanced": 407,
      "reviewed by": 408,
      "protects after": 409,
      "assess": 410,
      "expertise": 411,
      "contraindicated before": 412,
      "allow": 413,
      "may find": 414,
      "personalizes": 415,
      "dissolves": 416,
      "supplemented by": 417,
      "rapid feeding causes": 418,
      "coordinates": 419,
      "energy source for": 420,
      "publishes": 421,
      "\u9700\u8981\u8bc4\u4f30": 422,
      "increasing in": 423,
      "may regenerate": 424,
      "converts to": 425,
      "estimates": 426,
      "\u53ef\u4ee5\u4fc3\u8fdb": 427,
      "is associated with": 428,
      "documented via": 429,
      "uncommon in": 430,
      "limited by": 431,
      "faster acting than": 432,
      "impaired by": 433,
      "graded as": 434,
      "comparable to": 435,
      "indications": 436,
      "degrades by": 437,
      "can be staged with": 438,
      "skull fracture risks": 439,
      "traumatic strictures result from": 440,
      "has outcome": 441,
      "enteral feeding requires": 442,
      "is documented in": 443,
      "causes need for": 444,
      "contraindicated": 445,
      "wound closure": 446,
      "located in": 447,
      "occurs": 448,
      "corrected by": 449,
      "often follows": 450,
      "has indication": 451,
      "repositions": 452,
      "quantifies": 453,
      "helps determine": 454,
      "combine": 455,
      "operator-dependent": 456,
      "may obstruct": 457,
      "has risk of": 458,
      "teaches": 459,
      "processed for": 460,
      "applies to": 461,
      "carries risks": 462,
      "originates from": 463,
      "consists of": 464,
      "often combined with": 465,
      "goal of": 466,
      "monitored post": 467,
      "can convert to": 468,
      "affects results of": 469,
      "binds": 470,
      "surrounds": 471,
      "elevated in": 472,
      "alternative guidance for": 473,
      "signify": 474,
      "coordinates with": 475,
      "is part of": 476,
      "is contraindication for": 477,
      "transported via": 478,
      "aids recovery after": 479,
      "warns": 480,
      "possible with": 481,
      "mandated for": 482,
      "analyze": 483,
      "less effective than": 484,
      "radiation dose": 485,
      "neonatal benefits include": 486,
      "relates to": 487,
      "passes through": 488,
      "permits": 489,
      "progressed to": 490,
      "in elderly": 491,
      "grading system uses": 492,
      "aims to": 493,
      "affects outcome of": 494,
      "sufficient for": 495,
      "supplements with": 496,
      "track changes via": 497,
      "adjusted by": 498,
      "inhibited by": 499,
      "documentation includes": 500,
      "propagate via": 501,
      "work in": 502,
      "assessed with": 503,
      "stored as": 504,
      "bound to": 505,
      "chosen based on": 506,
      "relieve": 507,
      "requires precaution for": 508,
      "exacerbation requires": 509,
      "positions": 510,
      "long-term effect": 511,
      "methods include": 512,
      "metabolized into": 513,
      "may be outpatient": 514,
      "preoperative evaluation includes": 515,
      "removes part of": 516,
      "distinguishes": 517,
      "develops": 518,
      "forms behind": 519,
      "preventive measure": 520,
      "synthesized in": 521,
      "emergency indication": 522,
      "may damage": 523,
      "assist in": 524,
      "is diagnosed by": 525,
      "is focus of": 526,
      "tests": 527,
      "released from": 528,
      "considered when": 529,
      "can remove": 530,
      "scheduled after": 531,
      "reduce need for": 532,
      "risk factor for": 533,
      "cushions": 534,
      "is managed by": 535,
      "unit of": 536,
      "prescribe": 537,
      "observed by": 538,
      "potential need after": 539,
      "prescribed for": 540,
      "attacks": 541,
      "decrease": 542,
      "recommend": 543,
      "hold": 544,
      "GRV threshold determines": 545,
      "test": 546,
      "detected through": 547,
      "larger size for": 548,
      "gastric lavage removes": 549,
      "\u9700\u8981\u51c6\u5907": 550,
      "stimulates": 551,
      "upgraded with": 552,
      "enables": 553,
      "costs vary by": 554,
      "is controlled by": 555,
      "utilized by": 556,
      "line": 557,
      "pulmonary placement causes": 558,
      "necessitated by": 559,
      "important after": 560,
      "outcomes guide": 561,
      "\u662f": 562,
      "evolves with": 563,
      "used in": 564,
      "interferes with": 565,
      "has better outcomes": 566,
      "relies on": 567,
      "enlarges with": 568,
      "satisfaction rates exceed": 569,
      "can confirm": 570,
      "are selected by": 571,
      "integrates with": 572,
      "can place": 573,
      "characteristic of": 574,
      "may show": 575,
      "checked after": 576,
      "controlled with": 577,
      "audits": 578,
      "are also called": 579,
      "screens": 580,
      "complies": 581,
      "impact": 582,
      "store": 583,
      "gained through": 584,
      "fixes": 585,
      "mortality risk": 586,
      "has variable efficacy": 587,
      "commonly develop": 588,
      "prosthetic fitting": 589,
      "comorbid condition": 590,
      "allows visualization": 591,
      "alternates with": 592,
      "combined with": 593,
      "stands for": 594,
      "more frequently used than": 595,
      "sometimes complicates": 596,
      "excises": 597,
      "often require": 598,
      "immobilizes": 599,
      "monitors for": 600,
      "numbs": 601,
      "increase": 602,
      "spreads": 603,
      "classified as": 604,
      "recovery phase": 605,
      "adjusted based on": 606,
      "predicts outcome of": 607,
      "benchmarked with": 608,
      "mortality predictor": 609,
      "communicates with": 610,
      "less costly than": 611,
      "adjusted for": 612,
      "long-term use requires": 613,
      "prepares for": 614,
      "calculates": 615,
      "may increase": 616,
      "discontinued when": 617,
      "quality controlled by": 618,
      "measured by": 619,
      "possibly protective for": 620,
      "may progress to": 621,
      "occludes": 622,
      "informs": 623,
      "specialty of": 624,
      "identifiable by": 625,
      "visualized via": 626,
      "\u9700\u8981\u6392\u9664": 627,
      "connected to": 628,
      "are common": 629,
      "refers": 630,
      "convert": 631,
      "grows": 632,
      "aid": 633,
      "high residual indicates": 634,
      "mutate": 635,
      "outcome relates to": 636,
      "disrupted in": 637,
      "preserves": 638,
      "analyzes": 639,
      "limited for": 640,
      "certified by": 641,
      "evaluates": 642,
      "abnormal in": 643,
      "surgical approaches include": 644,
      "predisposes": 645,
      "integrate with": 646,
      "acquired through": 647,
      "has better cancer control than": 648,
      "monitored for": 649,
      "recurrence of": 650,
      "activated during": 651,
      "enters through": 652,
      "recorded in": 653,
      "measures": 654,
      "frequency depends on": 655,
      "has risk": 656,
      "less sensitive than": 657,
      "block": 658,
      "expelled via": 659,
      "spreads from": 660,
      "elective": 661,
      "emergency use": 662,
      "tightens": 663,
      "postoperative complication": 664,
      "\u53ef\u4ee5\u8bca\u65ad": 665,
      "varies by": 666,
      "standard in": 667,
      "colonizes": 668,
      "manifests as": 669,
      "aligns": 670,
      "generated by": 671,
      "marked": 672,
      "amplifies": 673,
      "lowers": 674,
      "may resolve": 675,
      "may influence": 676,
      "may be": 677,
      "mitigates": 678,
      "may use": 679,
      "analyzed by": 680,
      "raises": 681,
      "indicate": 682,
      "needed for": 683,
      "studied using": 684,
      "can refine": 685,
      "acts as": 686,
      "ordered by": 687,
      "can reveal": 688,
      "trains": 689,
      "used postoperatively": 690,
      "more responsive to": 691,
      "combines with": 692,
      "is essential for": 693,
      "posterior strictures involve": 694,
      "rehabilitation goal": 695,
      "overdose causes": 696,
      "secretes": 697,
      "prevalence low in": 698,
      "is used in": 699,
      "induce": 700,
      "heals in": 701,
      "not recommended by": 702,
      "expands": 703,
      "more likely in": 704,
      "patches": 705,
      "post-insertion care includes": 706,
      "complications include": 707,
      "sometimes indicated for": 708,
      "alters with": 709,
      "synonym for": 710,
      "performs": 711,
      "contrasts with": 712,
      "healing time": 713,
      "restored by": 714,
      "is radiation-free unlike": 715,
      "crossed by": 716,
      "investigated with": 717,
      "locates": 718,
      "advocates": 719,
      "reconstructs": 720,
      "encompass": 721,
      "placed in": 722,
      "delivers radiation": 723,
      "emergency from": 724,
      "sometimes combines": 725,
      "evaluated via": 726,
      "analysis detects": 727,
      "induces": 728,
      "can become": 729,
      "discovered by": 730,
      "promotes": 731,
      "coiled placement indicates": 732,
      "high-risk for": 733,
      "may spread": 734,
      "hospital stay": 735,
      "source of": 736,
      "form": 737,
      "are stored in": 738,
      "follows up": 739,
      "carried by": 740,
      "sometimes includes": 741,
      "increases with": 742,
      "uses technique": 743,
      "anterior strictures involve": 744,
      "wanes": 745,
      "widens": 746,
      "potential complication of": 747,
      "tolerate": 748,
      "affects difficulty of": 749,
      "may develop after": 750,
      "avoided with": 751,
      "can induce": 752,
      "speeds": 753,
      "places": 754,
      "Duke treadmill score": 755,
      "reveal": 756,
      "recommends": 757,
      "compares in": 758,
      "risk of": 759,
      "declines with": 760,
      "collects": 761,
      "alternative is": 762,
      "compared with": 763,
      "discusses": 764,
      "sterilize": 765,
      "motivates": 766,
      "sourced from": 767,
      "divides into": 768,
      "decreases risk": 769,
      "sustains": 770,
      "performed during": 771,
      "rapid test for": 772,
      "complication is": 773,
      "drives": 774,
      "refers to": 775,
      "can be from": 776,
      "used after": 777,
      "is cheaper than": 778,
      "can regenerate": 779,
      "attached to": 780,
      "removed by": 781,
      "may lead to": 782,
      "discharged with": 783,
      "curative for": 784,
      "may benefit": 785,
      "made of": 786,
      "debated in": 787,
      "\u7528\u4e8e": 788,
      "save": 789,
      "studied with": 790,
      "processes": 791,
      "sometimes used in": 792,
      "updated by": 793,
      "techniques include": 794,
      "originate in": 795,
      "maps": 796,
      "absorbed into": 797,
      "stained with": 798,
      "sacrifices": 799,
      "need": 800,
      "improve with": 801,
      "factor in": 802,
      "waste product of": 803,
      "preoperative use": 804,
      "inhibits": 805,
      "has higher resolution than": 806,
      "long term outcome": 807,
      "head elevation prevents": 808,
      "ends in": 809,
      "diverts": 810,
      "managed by": 811,
      "historically practiced by": 812,
      "provides functional information unlike": 813,
      "controversial in": 814,
      "interfere with": 815,
      "social impact": 816,
      "persists": 817,
      "administered after": 818,
      "misinterpreted by": 819,
      "post-procedure requires": 820,
      "encouraged for": 821,
      "innovation area": 822,
      "reinforces": 823,
      "compares with": 824,
      "elemental formula for": 825,
      "assists with": 826,
      "outdated by": 827,
      "certifies": 828,
      "researches": 829,
      "delivers": 830,
      "initiates at": 831,
      "monitors": 832,
      "control": 833,
      "completes": 834,
      "meets egg in": 835,
      "replaced by": 836,
      "ligated in": 837,
      "performed at": 838,
      "robot-assisted": 839,
      "has contraindications": 840,
      "protect against": 841,
      "potential for": 842,
      "indications based on": 843,
      "purple stripe indicates": 844,
      "vary by": 845,
      "inventories": 846,
      "venous embolization alternative to": 847,
      "is treated with": 848,
      "postoperative care includes": 849,
      "include": 850,
      "equipped with": 851,
      "reshapes": 852,
      "added to": 853,
      "balances": 854,
      "formula selection based on": 855,
      "vary in": 856,
      "documented as": 857,
      "terminus of": 858,
      "originate from": 859,
      "may yield": 860,
      "\u9700\u8981\u76d1\u6d4b": 861,
      "explored for": 862,
      "may necessitate": 863,
      "diagnosed by": 864,
      "invade": 865,
      "expands access to": 866,
      "assist": 867,
      "accompanies": 868,
      "METs measurement": 869,
      "follow-up": 870,
      "convenient for": 871,
      "prevents infection after": 872,
      "avoids": 873,
      "risk increases with": 874,
      "can suffer": 875,
      "merges": 876,
      "alternative": 877,
      "can repair": 878,
      "viewed on": 879,
      "specialty": 880,
      "prevents": 881,
      "emerging alternative to": 882,
      "reveals": 883,
      "relieved with": 884,
      "collected via": 885,
      "versus": 886,
      "urgent for": 887,
      "overcome by": 888,
      "transmit to": 889,
      "shows similar survival to": 890,
      "research improves": 891,
      "intra-abdominal testes require": 892,
      "governed by": 893,
      "quantified by": 894,
      "has higher complication rate than": 895,
      "straighten": 896,
      "synchronizes with": 897,
      "transmitted via": 898,
      "advance": 899,
      "localized in": 900,
      "cuts": 901,
      "often requires": 902,
      "setting for": 903,
      "pediatric version is": 904,
      "incorporates": 905,
      "preventable with": 906,
      "monitors after": 907,
      "risks": 908,
      "prescribed based on": 909,
      "relieved by": 910,
      "verified by": 911,
      "possible to": 912,
      "anesthesia type": 913,
      "selects": 914,
      "religious significance in": 915,
      "serves": 916,
      "retain": 917,
      "first performed in": 918,
      "characterizes": 919,
      "prescribed post": 920,
      "may heal": 921,
      "risks include": 922,
      "maintained by": 923,
      "limited in": 924,
      "controversial for": 925,
      "maintains": 926,
      "low in": 927,
      "scheduled as": 928,
      "have": 929,
      "special considerations for": 930,
      "not needed for": 931,
      "improves": 932,
      "irreversible in": 933,
      "prevalent in": 934,
      "adult procedure requires": 935,
      "has precaution": 936,
      "may attack": 937,
      "history": 938,
      "documents": 939,
      "can receive": 940,
      "stabilize": 941,
      "drapes": 942,
      "measured with": 943,
      "personalized for": 944,
      "have higher": 945,
      "post-op instructions include": 946,
      "biopsies": 947,
      "safe in": 948,
      "are killed by": 949,
      "converted by": 950,
      "supplemented with": 951,
      "first used in": 952,
      "available in": 953,
      "retrievable for": 954,
      "has lumen for": 955,
      "late complication of": 956,
      "side effect": 957,
      "generates": 958,
      "high output indicates": 959,
      "may harbor": 960,
      "reviewed in": 961,
      "detected by": 962,
      "performed by": 963,
      "remove": 964,
      "is common after": 965,
      "prohibited in": 966,
      "measured from": 967,
      "reduce": 968,
      "prevented with": 969,
      "mortality rate": 970,
      "has role": 971,
      "risks increase with": 972,
      "varies in": 973,
      "ensures": 974,
      "covered with": 975,
      "critical for": 976,
      "stages": 977,
      "material": 978,
      "is crucial in": 979,
      "surgical team includes": 980,
      "contain": 981,
      "commonly performed on": 982,
      "administered via": 983,
      "taken from": 984,
      "fostered in": 985,
      "emerging option for": 986,
      "evolving with": 987,
      "more effective in": 988,
      "life-threatening condition": 989,
      "crucial for": 990,
      "can collect": 991,
      "accumulation causes": 992,
      "relays": 993,
      "less time-consuming than": 994,
      "adult form associates with": 995,
      "is caused by": 996,
      "help with": 997,
      "shows hot spot in": 998,
      "combat": 999,
      "fragments": 1000,
      "recurrence requires": 1001,
      "aggregate into": 1002,
      "altered in": 1003,
      "examples are": 1004,
      "clears": 1005,
      "less specific than": 1006,
      "filters": 1007,
      "monitor for": 1008,
      "dangerous": 1009,
      "enhance": 1010,
      "anastomosed with": 1011,
      "rare in": 1012,
      "T1 mapping": 1013,
      "has layers": 1014,
      "followed by": 1015,
      "terminates for": 1016,
      "controlled by": 1017,
      "result from": 1018,
      "helpful for": 1019,
      "costs more than": 1020,
      "historical method": 1021,
      "prepare": 1022,
      "prolonged in": 1023,
      "red stripe indicates": 1024,
      "\u53ef\u4ee5\u7ed3\u5408": 1025,
      "smooths": 1026,
      "emergency": 1027,
      "examined with": 1028,
      "superseded by": 1029,
      "lines": 1030,
      "excreted via": 1031,
      "optional for": 1032,
      "bipolar technique reduces": 1033,
      "is site of": 1034,
      "requires regular": 1035,
      "recommended for": 1036,
      "prevention strategy": 1037,
      "have lower": 1038,
      "predispose to": 1039,
      "has religious significance in": 1040,
      "promises to transform": 1041,
      "confirms": 1042,
      "injected into": 1043,
      "emergency condition": 1044,
      "specializes in": 1045,
      "unsuitable for": 1046,
      "sometimes involves": 1047,
      "adjust": 1048,
      "responds": 1049,
      "involved in": 1050,
      "important for recovery after": 1051,
      "may affect": 1052,
      "assesses via": 1053,
      "frequently require": 1054,
      "may require": 1055,
      "can damage": 1056,
      "short-term use for": 1057,
      "are coordinated by": 1058,
      "real-time": 1059,
      "possible outcome of": 1060,
      "closed with": 1061,
      "responsible for": 1062,
      "may combine with": 1063,
      "help prevent": 1064,
      "risk communicated in": 1065,
      "known as": 1066,
      "rarely causes": 1067,
      "complicate": 1068,
      "considers": 1069,
      "rarely associates with": 1070,
      "inflames": 1071,
      "impairs": 1072,
      "restore": 1073,
      "compromised by": 1074,
      "advanced by": 1075,
      "pulls": 1076,
      "types include": 1077,
      "is a device for": 1078,
      "interprets": 1079,
      "common cause for": 1080,
      "offers better soft tissue contrast than": 1081,
      "absolutely contraindicated for": 1082,
      "researched for": 1083,
      "assesses": 1084,
      "approaches": 1085,
      "distinguished from": 1086,
      "processed with": 1087,
      "in obese patients": 1088,
      "coordinated with": 1089,
      "managed with": 1090,
      "highlights": 1091,
      "is alternative to": 1092,
      "varies for": 1093,
      "location of": 1094,
      "\u53ef\u4ee5\u68c0\u6d4b": 1095,
      "prevents seizures after": 1096,
      "identified through": 1097,
      "is necessary after": 1098,
      "oral hygiene prevents": 1099,
      "collected during": 1100,
      "rare complication": 1101,
      "reflect": 1102,
      "used during": 1103,
      "alters": 1104,
      "implements": 1105,
      "opens": 1106,
      "plans with": 1107,
      "may allow": 1108,
      "mediates": 1109,
      "checks": 1110,
      "postoperative symptom": 1111,
      "are at risk for": 1112,
      "is performed during": 1113,
      "attaches to": 1114,
      "generally safe for": 1115,
      "administers": 1116,
      "sources include": 1117,
      "more accurate than": 1118,
      "sometimes needed for": 1119,
      "pumps": 1120,
      "warns of": 1121,
      "contains": 1122,
      "use": 1123,
      "stratify": 1124,
      "relate to": 1125,
      "follows discharge after": 1126,
      "challenge": 1127,
      "drain": 1128,
      "helps in": 1129,
      "commonly used for": 1130,
      "protects": 1131,
      "infection may require": 1132,
      "success depends on": 1133,
      "measure": 1134,
      "can correct": 1135,
      "transport": 1136,
      "encloses": 1137,
      "separates": 1138,
      "rescheduled after": 1139,
      "has longer recovery than": 1140,
      "ordered for": 1141,
      "has survival rate": 1142,
      "preferred site": 1143,
      "help": 1144,
      "bilious output indicates": 1145,
      "transported to": 1146,
      "cause less": 1147,
      "more precise than": 1148,
      "may need adjustment before": 1149,
      "linked to": 1150,
      "incompatible with": 1151,
      "may be used in": 1152,
      "team includes": 1153,
      "recommended annually": 1154,
      "medical term for": 1155,
      "has limitation": 1156,
      "reaches": 1157,
      "increases need for": 1158,
      "prevalence increases with": 1159,
      "coordinated by": 1160,
      "performed with": 1161,
      "performed without": 1162,
      "declining in": 1163,
      "weakens": 1164,
      "can dilate": 1165,
      "less frequent in": 1166,
      "can be relieved by": 1167,
      "shows": 1168,
      "contribute to": 1169,
      "deals with": 1170,
      "accesses": 1171,
      "prepare for": 1172,
      "protect": 1173,
      "are developed in": 1174,
      "risk after": 1175,
      "is faster than": 1176,
      "delivered by": 1177,
      "follow-up for": 1178,
      "shows increased uptake in": 1179,
      "reimburses": 1180,
      "has higher cost than": 1181,
      "can use": 1182,
      "absorbs": 1183,
      "aims for": 1184,
      "discharge planning": 1185,
      "replacement recommended after": 1186,
      "prevent infection after": 1187,
      "produced by": 1188,
      "bypasses": 1189,
      "may inform": 1190,
      "obstructed in": 1191,
      "has risk factor": 1192,
      "whole-body": 1193,
      "overturned in": 1194,
      "follow-up includes": 1195,
      "sometimes causes": 1196,
      "preoperative test": 1197,
      "recurrence after": 1198,
      "increases": 1199,
      "handle": 1200,
      "recovers within": 1201,
      "has cost": 1202,
      "not for": 1203,
      "focuses": 1204,
      "preferred for": 1205,
      "complemented by": 1206,
      "may interact with": 1207,
      "disposes": 1208,
      "treat": 1209,
      "remains": 1210,
      "cited in": 1211,
      "patient education": 1212,
      "provides detailed images": 1213,
      "necessary after": 1214,
      "failure rate depends on": 1215,
      "indicates": 1216,
      "is altered by": 1217,
      "withheld before": 1218,
      "for": 1219,
      "inferior for": 1220,
      "prevent": 1221,
      "causes": 1222,
      "relax": 1223,
      "rarely undergo": 1224,
      "limit": 1225,
      "is available for": 1226,
      "in smokers": 1227,
      "cost-effective": 1228,
      "eligible for": 1229,
      "higher radiation than": 1230,
      "reflects": 1231,
      "achieved via": 1232,
      "depends on": 1233,
      "timed with": 1234,
      "removed after": 1235,
      "diastolic assessment": 1236,
      "spreads to": 1237,
      "employ": 1238,
      "transports": 1239,
      "saves": 1240,
      "filtered by": 1241,
      "normalizes": 1242,
      "terminates": 1243,
      "performed after": 1244,
      "is corrected by": 1245,
      "monitoring": 1246,
      "connect to": 1247,
      "more accessible than": 1248,
      "arises from": 1249,
      "differs by": 1250,
      "grades": 1251,
      "taught by": 1252,
      "may evolve with": 1253,
      "is an option for": 1254,
      "defined as": 1255,
      "used when": 1256,
      "progresses": 1257,
      "limits": 1258,
      "sometimes results in": 1259,
      "oversee": 1260,
      "emergency during": 1261,
      "regulates": 1262,
      "gold standard for": 1263,
      "require special consideration for": 1264,
      "shared among": 1265,
      "absorbed by": 1266,
      "help diagnose": 1267,
      "applied with": 1268,
      "facilitate": 1269,
      "can prevent": 1270,
      "differentiates": 1271,
      "stored under": 1272,
      "should be": 1273,
      "may precede": 1274,
      "sometimes covered by": 1275,
      "is evaluated by": 1276,
      "metoclopramide increases": 1277,
      "applicable in": 1278,
      "examined under": 1279,
      "facilitates": 1280,
      "inserted through": 1281,
      "activates": 1282,
      "color coding indicates": 1283,
      "recommended after": 1284,
      "resects": 1285,
      "recovers": 1286,
      "may reduce": 1287,
      "customizable for": 1288,
      "often in": 1289,
      "indicates need for": 1290,
      "prognostic for": 1291,
      "aided by": 1292,
      "celebrated in": 1293,
      "treated in": 1294,
      "may contain": 1295,
      "provides setting for": 1296,
      "takes": 1297,
      "risk assessed via": 1298,
      "drains": 1299,
      "damage": 1300,
      "can influence": 1301,
      "wears off": 1302,
      "noninvasive": 1303,
      "important during": 1304,
      "connect": 1305,
      "neutralizes": 1306,
      "may be needed for": 1307,
      "placed with": 1308,
      "location": 1309,
      "can be assessed with": 1310,
      "optimize": 1311,
      "surgical team": 1312,
      "avoided by": 1313,
      "obstructed by": 1314,
      "networks": 1315,
      "duration typically": 1316,
      "supplement": 1317,
      "can displace": 1318,
      "more detailed than": 1319,
      "also called": 1320,
      "prohibits": 1321,
      "establishes": 1322,
      "identifies": 1323,
      "promote": 1324,
      "deteriorates in": 1325,
      "graded by": 1326,
      "connects to": 1327,
      "is used by": 1328,
      "monitored through": 1329,
      "dissected with": 1330,
      "first used": 1331,
      "has color": 1332,
      "benefits outweigh risks in": 1333,
      "is precursor of": 1334,
      "monitored before": 1335,
      "secured with": 1336,
      "early form of": 1337,
      "RELATIONSHIP": 1338,
      "may compress": 1339,
      "most commonly performed on": 1340,
      "complication of": 1341,
      "advances": 1342,
      "\u53ef\u4ee5\u7f29\u77ed": 1343,
      "strengthens": 1344,
      "uses": 1345,
      "reimbursed by": 1346,
      "rehabilitation after": 1347,
      "sometimes used for": 1348,
      "specialize in": 1349,
      "aggravates": 1350,
      "reported in": 1351,
      "accommodates": 1352,
      "selected based on": 1353,
      "restricts": 1354,
      "gating technique": 1355,
      "assessed through": 1356,
      "helps adjust": 1357,
      "differs from": 1358,
      "are a type of": 1359,
      "recovery time": 1360,
      "places radiation source": 1361,
      "allow access to": 1362,
      "rare complication of": 1363,
      "can strengthen": 1364,
      "alternative technique": 1365,
      "vascular consideration": 1366,
      "coded with": 1367,
      "classifies": 1368,
      "hormonal therapy adjunct to": 1369,
      "confirmed by": 1370,
      "accessible in": 1371,
      "may relate to": 1372,
      "influenced by": 1373,
      "is indication for": 1374,
      "opposed by": 1375,
      "adheres to": 1376,
      "improved by": 1377,
      "provoke": 1378,
      "technique": 1379,
      "interpreted by": 1380,
      "reviews": 1381,
      "target": 1382,
      "helps plan": 1383,
      "coded as": 1384,
      "originates in": 1385,
      "often reduced after": 1386,
      "isolates": 1387,
      "isolate": 1388,
      "moves": 1389,
      "given for": 1390,
      "evaluates with": 1391,
      "yellow stripe indicates": 1392,
      "sometimes involve": 1393,
      "may help": 1394,
      "are alternatives for": 1395,
      "penetrates deeper into": 1396,
      "difficult after": 1397,
      "monitor after": 1398,
      "is linked to": 1399,
      "provided in": 1400,
      "generate": 1401,
      "side effect of": 1402,
      "\u4f7f\u7528": 1403,
      "can obstruct": 1404,
      "functions as": 1405,
      "enhances": 1406,
      "prokinetics improve": 1407,
      "removes entire": 1408,
      "prevented by": 1409,
      "anticipates": 1410,
      "has improved with": 1411,
      "reduces need for": 1412,
      "expand": 1413,
      "readmission rate": 1414,
      "is similar to": 1415,
      "screens for": 1416,
      "related to": 1417,
      "monitored in": 1418,
      "accessed through": 1419,
      "duration depends on": 1420,
      "elective for": 1421,
      "secrete": 1422,
      "obtained from": 1423,
      "precursor to": 1424,
      "mimic": 1425,
      "not used for": 1426,
      "staffed by": 1427,
      "precede": 1428,
      "assists": 1429,
      "stabilized by": 1430,
      "is common for": 1431,
      "supplies blood to": 1432,
      "\u53ef\u4ee5\u964d\u4f4e": 1433,
      "benchmarks": 1434,
      "adjustable": 1435,
      "heal over": 1436,
      "creates cross-sectional images": 1437,
      "measured for": 1438,
      "discussed in": 1439,
      "symptom relief": 1440,
      "often precedes": 1441,
      "spares": 1442,
      "scheduled": 1443,
      "allows for": 1444,
      "can help diagnose": 1445,
      "affect": 1446,
      "assisted by": 1447,
      "traps": 1448,
      "documented in": 1449,
      "contraindication": 1450,
      "elevates": 1451,
      "collaborate on": 1452,
      "technique taught in": 1453,
      "supplements": 1454,
      "partially": 1455,
      "may improve": 1456,
      "has benefit": 1457,
      "tracks": 1458,
      "reintervention rate": 1459,
      "has shorter": 1460,
      "advancement": 1461,
      "covered by": 1462,
      "research focuses on": 1463,
      "fuels": 1464,
      "can involve": 1465,
      "quality of life": 1466,
      "normally occurs in": 1467,
      "are part of": 1468,
      "vibrates with": 1469,
      "option for": 1470,
      "outpatient use monitored by": 1471,
      "fertilized by": 1472,
      "researched via": 1473,
      "target of": 1474,
      "performed on": 1475,
      "research focus": 1476,
      "complement": 1477,
      "applied after": 1478,
      "innervated by": 1479,
      "are detected in": 1480,
      "are targeted by": 1481,
      "can have": 1482,
      "technique for": 1483,
      "activated by": 1484,
      "is": 1485,
      "cost varies by": 1486,
      "important for": 1487,
      "processed in": 1488,
      "is safer than": 1489,
      "handles": 1490,
      "occurs after": 1491,
      "dissolve": 1492,
      "diffuse across": 1493,
      "sometimes replaced by": 1494,
      "exercise version": 1495,
      "evaluated by": 1496,
      "hindered by": 1497,
      "Fowler-Stephens technique preserves": 1498,
      "may include": 1499,
      "administer": 1500,
      "has higher efficacy": 1501,
      "minimizes": 1502,
      "assists in analyzing": 1503,
      "continuous suction used for": 1504,
      "predicts": 1505,
      "grows into": 1506,
      "restrict": 1507,
      "effectiveness confirmed via": 1508,
      "coded using": 1509,
      "educates about": 1510,
      "delivered via": 1511,
      "may complement": 1512,
      "has approach": 1513,
      "monitored during": 1514,
      "modifies": 1515,
      "antibiotic prophylaxis": 1516,
      "disputed in": 1517,
      "malleable type simpler but": 1518,
      "suitable for": 1519,
      "produces": 1520,
      "clogging prevented by": 1521,
      "\u53ef\u4ee5\u8bc4\u4f30": 1522,
      "superior to": 1523,
      "essential for": 1524,
      "updated": 1525,
      "contracts": 1526,
      "technique involves": 1527,
      "host": 1528,
      "govern": 1529,
      "recommended post": 1530,
      "\u540e\u9700\u8981": 1531,
      "shrinks": 1532,
      "corresponds to": 1533,
      "quality measured by": 1534,
      "uses instrument": 1535,
      "attempted with": 1536,
      "alerts": 1537,
      "restricted by": 1538,
      "explained through": 1539,
      "prognosis depends on": 1540,
      "disorders include": 1541,
      "challenging for": 1542,
      "runs through": 1543,
      "may worsen after": 1544,
      "studies": 1545,
      "has worse": 1546,
      "explains": 1547,
      "tracked in": 1548,
      "can deliver": 1549,
      "trialing": 1550,
      "heals slower than": 1551,
      "timing at": 1552,
      "instrument for": 1553,
      "are measured by": 1554,
      "relates": 1555,
      "correlated with": 1556,
      "registry data": 1557,
      "may remove": 1558,
      "possible during": 1559,
      "innovates": 1560,
      "contraindicated in": 1561,
      "quicker than": 1562,
      "based on": 1563,
      "fight": 1564,
      "are treated by": 1565,
      "common": 1566,
      "creates": 1567,
      "monitor": 1568,
      "laparoscopic approach benefits": 1569,
      "may depend on": 1570,
      "may worsen": 1571,
      "has standard": 1572,
      "localizes": 1573,
      "pushes": 1574,
      "may correlate with": 1575,
      "considered for": 1576,
      "may lead": 1577,
      "commonly causes": 1578,
      "attracts": 1579,
      "sometimes uses": 1580,
      "less expensive than": 1581,
      "possible in": 1582,
      "carries": 1583,
      "may be needed": 1584,
      "3D version": 1585,
      "worsened by": 1586,
      "guides": 1587,
      "can be examined by": 1588,
      "captures": 1589,
      "evolved from": 1590,
      "sends": 1591,
      "preoperative preparation includes": 1592,
      "has subtypes": 1593,
      "undergoes": 1594,
      "may follow": 1595,
      "break down": 1596,
      "mitigated by": 1597,
      "lightweight material for": 1598,
      "cushioned by": 1599,
      "helps rule out": 1600,
      "mediate": 1601,
      "feature tracking": 1602,
      "occur in": 1603,
      "arranges": 1604,
      "indicated by": 1605,
      "optimal for": 1606,
      "loosens": 1607,
      "may replace": 1608,
      "neutralized by": 1609,
      "rebuilt through": 1610,
      "Doppler mode": 1611,
      "more widely available than": 1612,
      "optimized by": 1613,
      "also used for": 1614,
      "drained with": 1615,
      "more specific than": 1616,
      "has marking for": 1617,
      "can be evaluated by": 1618,
      "fails more than": 1619,
      "studied in": 1620,
      "assist with": 1621,
      "worsens": 1622,
      "performed in": 1623,
      "guided by": 1624,
      "impair": 1625,
      "cost affected by": 1626,
      "contours": 1627,
      "adapts for": 1628,
      "cost-effectiveness": 1629,
      "can cause": 1630,
      "has less pain": 1631,
      "no risk of": 1632,
      "suppress": 1633,
      "impaired in": 1634,
      "is a technique of": 1635,
      "risks vary by": 1636,
      "instrument": 1637,
      "excludes": 1638,
      "corrects": 1639,
      "obstructs": 1640,
      "protected by": 1641,
      "often includes": 1642,
      "transmit": 1643,
      "rules out": 1644,
      "usually follows": 1645,
      "subclass of": 1646,
      "secure": 1647,
      "advances with": 1648,
      "may accompany": 1649,
      "validates": 1650,
      "transformed by": 1651,
      "supply": 1652,
      "tested by": 1653,
      "more complex than": 1654,
      "more invasive than": 1655,
      "three-piece type includes": 1656,
      "educates": 1657,
      "historical use": 1658,
      "has better": 1659,
      "standardizes": 1660,
      "softens": 1661,
      "transported by": 1662,
      "can improve": 1663,
      "legalized in": 1664,
      "optimal timing before": 1665,
      "violated by": 1666,
      "nursing care": 1667,
      "learning curve": 1668,
      "may miss": 1669,
      "is site for": 1670,
      "avoided after": 1671,
      "slow feeding prevents": 1672,
      "may decrease": 1673,
      "reduces risk": 1674,
      "antagonized by": 1675,
      "may be combined with": 1676,
      "used with": 1677,
      "removes": 1678,
      "consulted with": 1679,
      "sampled for": 1680,
      "research involves": 1681,
      "improve": 1682,
      "avoided before": 1683,
      "coded in": 1684,
      "participates in": 1685,
      "impacts": 1686,
      "planned for": 1687,
      "controls": 1688,
      "has": 1689,
      "constricts": 1690,
      "determines": 1691,
      "verifies": 1692,
      "lower risk than": 1693,
      "may persist after": 1694,
      "has higher morbidity than": 1695,
      "developed to support": 1696,
      "can alter": 1697,
      "complex cases require": 1698,
      "sometimes preceded by": 1699,
      "preceded by": 1700,
      "spread": 1701,
      "achieved through": 1702,
      "helps detect": 1703,
      "shapes": 1704,
      "is less invasive than": 1705,
      "decreases with": 1706,
      "apply to": 1707,
      "heals": 1708,
      "is type of": 1709,
      "coated with": 1710,
      "correct": 1711,
      "alternative treatment": 1712,
      "reversible via": 1713,
      "progressive": 1714,
      "FFR-CT": 1715,
      "minimized by": 1716,
      "transmits": 1717,
      "may consider": 1718,
      "supports": 1719,
      "aid in": 1720,
      "plaque characterization": 1721,
      "exacerbates": 1722,
      "overuse leads": 1723,
      "diagnosed through": 1724,
      "concern in": 1725,
      "cosmetic concern after": 1726,
      "interpreted using": 1727,
      "substitutes for": 1728,
      "alerts to": 1729,
      "diagnoses": 1730,
      "correlates": 1731,
      "possible after": 1732,
      "longer recovery than": 1733,
      "Salem sump type has": 1734,
      "converted to": 1735,
      "subclinical form detected via": 1736,
      "visualize": 1737,
      "produced in": 1738,
      "relaxes": 1739,
      "is a category of": 1740,
      "degrades": 1741,
      "combats": 1742,
      "associated disease": 1743,
      "adjunct to": 1744,
      "measures by": 1745,
      "more effective than": 1746,
      "reversed by": 1747,
      "refined via": 1748,
      "have higher risk with": 1749,
      "absorbed in": 1750,
      "utilizes": 1751,
      "bypassed by": 1752,
      "helps identify": 1753,
      "first-line treatment for": 1754,
      "contraindicate": 1755,
      "identify": 1756,
      "performed for": 1757,
      "ensure": 1758,
      "justifies": 1759,
      "can assess": 1760,
      "can develop": 1761,
      "enhanced by": 1762,
      "aim for": 1763,
      "positioned in": 1764,
      "is required for": 1765,
      "contraindications include": 1766,
      "exposes": 1767,
      "subject to": 1768,
      "may induce": 1769,
      "can address": 1770,
      "lowered by": 1771,
      "performed under": 1772,
      "orders": 1773,
      "harvested from": 1774,
      "has variation": 1775,
      "compares": 1776,
      "allow for": 1777,
      "can undergo": 1778,
      "shortens": 1779,
      "has part": 1780,
      "common in": 1781,
      "size measured in": 1782,
      "requires precautions in": 1783,
      "final step of": 1784,
      "published by": 1785,
      "require specialized": 1786,
      "is relieved by": 1787,
      "obstruct": 1788,
      "classified by": 1789,
      "is prescribed by": 1790,
      "quality indicator": 1791,
      "may enhance": 1792,
      "reimbursement depends": 1793,
      "placed by": 1794,
      "analyzed in": 1795,
      "exclude": 1796,
      "consents to": 1797,
      "boost": 1798,
      "component of": 1799,
      "oversees": 1800,
      "join": 1801,
      "modes include": 1802,
      "nourishes": 1803,
      "visualizes": 1804,
      "selects for": 1805,
      "excluded via": 1806,
      "risk includes": 1807,
      "may change after": 1808,
      "carry": 1809,
      "preserved by": 1810,
      "destroys": 1811,
      "localized to": 1812,
      "leads to": 1813,
      "emerging for": 1814,
      "can correlate with": 1815,
      "deficiency causes": 1816,
      "achieved by": 1817,
      "effective against": 1818,
      "may impact": 1819,
      "gives rise to": 1820,
      "sign of infection after": 1821,
      "archived in": 1822,
      "records": 1823,
      "suggest": 1824,
      "done by": 1825,
      "inserted by": 1826,
      "has learning curve": 1827,
      "symptom of": 1828,
      "often followed by": 1829,
      "irritates": 1830,
      "impacted by": 1831,
      "has lower risk": 1832,
      "first-line for": 1833,
      "such as": 1834,
      "empowers": 1835,
      "is non-invasive": 1836,
      "boosts": 1837,
      "preoperative preparation": 1838,
      "delayed in": 1839,
      "necessary for": 1840,
      "insertion technique affects": 1841,
      "cost-effective for": 1842,
      "precursor of": 1843,
      "may complicate": 1844,
      "reduces need": 1845,
      "rehabilitation includes": 1846,
      "dressing": 1847,
      "retrains": 1848,
      "pharmacological option": 1849,
      "used for pain after": 1850,
      "success measured by": 1851,
      "minimize": 1852,
      "is an": 1853,
      "cleaved by": 1854,
      "can lead to": 1855,
      "has side effect": 1856,
      "assess for": 1857,
      "leaves": 1858,
      "is a tracer for": 1859,
      "indication for": 1860,
      "indicated for": 1861,
      "future of": 1862,
      "can be increased by": 1863,
      "tool for": 1864,
      "more costly than": 1865,
      "degenerates": 1866,
      "stable in": 1867,
      "penetrates": 1868,
      "patient education includes": 1869,
      "flushed with": 1870,
      "equipment": 1871,
      "performed via": 1872,
      "is performed by": 1873,
      "risk factors": 1874,
      "lack": 1875,
      "higher in": 1876,
      "large glands require": 1877,
      "comprises": 1878,
      "sometimes performed during": 1879,
      "replaced after": 1880,
      "can perform": 1881,
      "reflected in": 1882,
      "alternative access for": 1883,
      "may recur": 1884,
      "mobilizes": 1885,
      "stored in": 1886,
      "compromised in": 1887,
      "inserts": 1888,
      "contraindicated with": 1889,
      "permanent": 1890,
      "most common type": 1891,
      "processed by": 1892,
      "tailors": 1893,
      "training includes": 1894,
      "may be due to": 1895,
      "more sensitive than": 1896,
      "achieved with": 1897,
      "more common in": 1898,
      "common site for": 1899,
      "damaged by": 1900,
      "standardized by": 1901,
      "can trigger": 1902,
      "avoided prior to": 1903,
      "at risk during": 1904,
      "integrates": 1905,
      "vaccinates": 1906,
      "innovation": 1907,
      "more severe than": 1908,
      "replaces": 1909,
      "stimulate": 1910,
      "prevention": 1911,
      "perform": 1912,
      "influences": 1913,
      "has advantage": 1914,
      "assessed for": 1915,
      "congenital": 1916,
      "can lead": 1917,
      "modulates": 1918,
      "cost factor": 1919,
      "higher risk than": 1920,
      "metabolizes": 1921,
      "reports": 1922,
      "includes": 1923,
      "section of": 1924,
      "composed of": 1925,
      "schedules": 1926,
      "provides": 1927,
      "are treated with": 1928,
      "non-invasive alternative to": 1929,
      "improved through": 1930,
      "patient selection": 1931,
      "numbed with": 1932,
      "more cost-effective than": 1933,
      "predict": 1934,
      "takes longer than": 1935,
      "relieves": 1936,
      "cover": 1937,
      "damages": 1938,
      "reviewed with": 1939,
      "circulates": 1940,
      "guideline": 1941,
      "weighted tip assists": 1942,
      "research area": 1943,
      "coagulates": 1944,
      "inhibit": 1945,
      "benefits": 1946,
      "assistive device": 1947,
      "emergency use includes": 1948,
      "ensured by": 1949,
      "result of": 1950,
      "home use requires": 1951,
      "blood pressure response": 1952,
      "aggravated by": 1953,
      "declined by": 1954,
      "higher risk": 1955,
      "lowers risk": 1956,
      "focuses on": 1957,
      "mimics": 1958,
      "late enhancement": 1959,
      "has component": 1960,
      "clarified by": 1961,
      "complications": 1962,
      "is basis of": 1963,
      "timing depends on": 1964,
      "unweighted tip is": 1965,
      "becomes": 1966,
      "may thicken": 1967,
      "recovery involves": 1968,
      "prefers": 1969,
      "is a side effect of": 1970,
      "opposes": 1971,
      "necessitates": 1972,
      "identified via": 1973,
      "redirects": 1974,
      "sometimes delays": 1975,
      "support": 1976,
      "cares for": 1977,
      "needed after": 1978,
      "may treat": 1979,
      "augments": 1980,
      "mentioned in": 1981,
      "leads": 1982,
      "common symptom": 1983,
      "innovates with": 1984,
      "is higher for": 1985,
      "escapes": 1986,
      "referenced in": 1987,
      "may progress after": 1988,
      "resists": 1989,
      "inserted into": 1990,
      "invented by": 1991,
      "triggered by": 1992,
      "factors include": 1993,
      "prescribed by": 1994,
      "evaluates for": 1995,
      "benchmark": 1996,
      "altered by": 1997,
      "evaluated for": 1998,
      "specializes": 1999,
      "improves with": 2000,
      "triggers": 2001,
      "worsens with": 2002,
      "provided at": 2003,
      "can identify": 2004,
      "reattaches to": 2005,
      "increase risk of": 2006,
      "sometimes avoids": 2007,
      "perceived by": 2008,
      "performed earlier than": 2009,
      "costs less than": 2010,
      "designs": 2011,
      "granted by": 2012,
      "exploring": 2013,
      "approaches include": 2014,
      "address": 2015,
      "governs": 2016,
      "marker for": 2017,
      "responds well to": 2018,
      "part of": 2019,
      "characterized by": 2020,
      "diagnostic tool for": 2021,
      "can be evaluated with": 2022,
      "involve": 2023,
      "can restore": 2024,
      "less effective for": 2025,
      "can diagnose": 2026,
      "places embryo in": 2027,
      "contraindicates": 2028,
      "useful in": 2029,
      "may detect": 2030,
      "improves safety of": 2031,
      "may vary by": 2032,
      "visible on": 2033,
      "nurtures": 2034,
      "preparation includes": 2035,
      "identified by": 2036,
      "links to": 2037,
      "compensates": 2038,
      "aids": 2039,
      "has characteristic": 2040,
      "used for": 2041,
      "treated with": 2042,
      "sometimes performed": 2043,
      "may be needed after": 2044,
      "given as": 2045,
      "connected by": 2046,
      "determine": 2047,
      "undergo": 2048,
      "intermittent suction prevents": 2049,
      "has application": 2050,
      "may not need": 2051,
      "evaluated through": 2052,
      "helps": 2053,
      "contrasts": 2054,
      "close": 2055,
      "detect": 2056,
      "complements": 2057,
      "contraindicated for": 2058,
      "source can be": 2059,
      "cause": 2060,
      "sutures": 2061,
      "is preferred": 2062,
      "social aspects include": 2063,
      "has recurrence rate": 2064,
      "updates": 2065,
      "possible for": 2066,
      "digested in": 2067,
      "less common than": 2068,
      "may recommend": 2069,
      "is method for": 2070,
      "emits": 2071,
      "examined by": 2072,
      "has minimal": 2073,
      "endpoint": 2074,
      "risk for": 2075,
      "minimally invasive": 2076,
      "faster than": 2077,
      "have risk of": 2078,
      "calibrates": 2079,
      "may result": 2080,
      "false positives": 2081,
      "permitted for": 2082,
      "repeated for": 2083,
      "forms": 2084,
      "packs": 2085,
      "normal range": 2086,
      "are a": 2087,
      "destroyed by": 2088,
      "may refer to": 2089,
      "visualized with": 2090,
      "prioritizes": 2091,
      "polymeric formula is": 2092,
      "need careful management after": 2093,
      "exacerbated by": 2094,
      "draped in": 2095,
      "consent involves": 2096,
      "\u53ef\u4ee5\u8bf1\u53d1": 2097,
      "allows": 2098,
      "options include": 2099,
      "attaches": 2100,
      "labels": 2101,
      "effectiveness depends on": 2102,
      "has failure rate": 2103,
      "Levin type is": 2104,
      "potentially reversible in": 2105,
      "under development for": 2106,
      "remains for": 2107,
      "primary cause of": 2108,
      "aids in": 2109,
      "outcome measure of": 2110,
      "less effective in": 2111,
      "activated charcoal delivered via": 2112,
      "has odor": 2113,
      "refines": 2114,
      "common symptom after": 2115,
      "duration": 2116,
      "may develop": 2117,
      "introduces": 2118,
      "can affect": 2119,
      "causes include": 2120,
      "is regulated by": 2121,
      "outcome measure": 2122,
      "non-invasive": 2123,
      "sometimes requires": 2124,
      "sometimes necessitates": 2125,
      "permanent in": 2126,
      "more rapid than": 2127,
      "resistant to": 2128,
      "slows": 2129,
      "diagnostic test": 2130,
      "higher prevalence in": 2131,
      "accelerates": 2132,
      "calibrated for": 2133,
      "conducts": 2134,
      "medication administration requires": 2135,
      "affects recovery from": 2136,
      "affected by": 2137,
      "mechanism": 2138,
      "confirmed via": 2139,
      "illuminates": 2140,
      "maintain": 2141,
      "imaging for": 2142,
      "lined by": 2143,
      "imbalance causes": 2144,
      "derived from": 2145,
      "is a risk of": 2146,
      "sensitive to": 2147,
      "collaborates": 2148,
      "preventable via": 2149,
      "basis of": 2150,
      "remains essential": 2151,
      "contributes to": 2152,
      "decreases": 2153,
      "deliver": 2154,
      "explained with": 2155,
      "is a method of": 2156,
      "determined by": 2157,
      "needs": 2158,
      "sometimes followed by": 2159,
      "nutritional need": 2160,
      "taught in": 2161,
      "utilized in": 2162,
      "injects": 2163,
      "track": 2164,
      "avoid": 2165,
      "changes during": 2166,
      "lower risk": 2167,
      "recovery heart rate": 2168,
      "researched in": 2169,
      "closes with": 2170,
      "screened by": 2171,
      "provides higher resolution": 2172,
      "compares to": 2173,
      "interrupts": 2174,
      "lubricates": 2175,
      "benefits outweigh": 2176,
      "less detailed than": 2177,
      "at risk for": 2178,
      "minimized with": 2179,
      "researching": 2180,
      "consideration for": 2181,
      "result in": 2182,
      "hereditary in": 2183,
      "may involve": 2184,
      "is reversible via": 2185,
      "developed by": 2186,
      "contraindications": 2187,
      "may need": 2188,
      "has types": 2189,
      "assessed during": 2190,
      "has type": 2191,
      "susceptible to": 2192,
      "treatment for": 2193,
      "placed near": 2194,
      "improves detection of": 2195,
      "relative contraindication for": 2196,
      "tracked with": 2197,
      "monitored by": 2198,
      "hijacked by": 2199,
      "diagnostic tests include": 2200,
      "educate about": 2201,
      "prescribed after": 2202,
      "has faster recovery": 2203,
      "sometimes precedes": 2204,
      "has no": 2205,
      "risks explained in": 2206,
      "demand": 2207,
      "carries risk of": 2208,
      "strengthen": 2209,
      "conserves": 2210,
      "has limited": 2211,
      "sometimes paired with": 2212,
      "calculated using": 2213,
      "diagnosed via": 2214,
      "has outcome measure": 2215,
      "exchange": 2216,
      "blood loss": 2217,
      "damaged in": 2218,
      "cleans": 2219,
      "psychological aspects include": 2220,
      "complication": 2221,
      "monitoring during": 2222,
      "can be detected by": 2223,
      "tested for": 2224,
      "has CPT code": 2225,
      "evaluate": 2226,
      "has cultural significance in": 2227,
      "is detected by": 2228,
      "has been used": 2229,
      "implant": 2230,
      "restricted during": 2231,
      "may result from": 2232,
      "can complicate": 2233,
      "increased by": 2234,
      "helps with": 2235,
      "studied by": 2236,
      "begins": 2237,
      "monitored with": 2238,
      "has procedure time": 2239,
      "helps prevent": 2240,
      "future": 2241,
      "benefit from": 2242,
      "has recovery time": 2243,
      "more affordable than": 2244,
      "prepares": 2245,
      "positioned near": 2246,
      "standard for": 2247,
      "located near": 2248,
      "speeds up": 2249,
      "insurance coverage": 2250,
      "miniaturized in": 2251,
      "generated in": 2252,
      "consist of": 2253,
      "helps manage": 2254,
      "emerging": 2255,
      "manages": 2256,
      "heals by": 2257,
      "avoided in": 2258,
      "flushes": 2259,
      "left side predominance due to": 2260,
      "rely on": 2261,
      "may indicate": 2262,
      "plans": 2263,
      "classification": 2264,
      "facilitated by": 2265,
      "synthesized by": 2266,
      "protects from": 2267,
      "can relieve": 2268,
      "complementary to": 2269,
      "is a complication of": 2270,
      "protects against": 2271,
      "postoperative requires": 2272,
      "sometimes avoided via": 2273,
      "completes with": 2274,
      "formed from": 2275,
      "more durable than": 2276,
      "is influenced by": 2277,
      "sometimes prevents": 2278,
      "influence": 2279,
      "alleviated by": 2280,
      "stops": 2281,
      "sometimes guided by": 2282,
      "combine with": 2283,
      "example": 2284,
      "tested using": 2285,
      "has better long-term results than": 2286,
      "reversed with": 2287,
      "examples": 2288,
      "are": 2289,
      "may undergo": 2290,
      "activate": 2291,
      "examined via": 2292,
      "adds to": 2293,
      "resolves": 2294,
      "patient position": 2295,
      "\u9700\u8981\u8bb0\u5f55": 2296,
      "strain imaging": 2297,
      "\u53ef\u80fd\u5bfc\u81f4": 2298,
      "transplants": 2299,
      "prepared with": 2300,
      "narrows in": 2301,
      "stretches": 2302,
      "processed as": 2303,
      "create": 2304,
      "prosthetic component": 2305,
      "can obtain": 2306,
      "may become": 2307,
      "preferred in": 2308,
      "temporary": 2309,
      "suggests": 2310,
      "kills": 2311,
      "has longer operative time than": 2312,
      "taught using": 2313,
      "cheaper than": 2314,
      "build": 2315,
      "seals": 2316,
      "can combine with": 2317,
      "trigger": 2318,
      "found in": 2319,
      "spreads by": 2320,
      "adjusts": 2321,
      "no radiation": 2322,
      "individualized for": 2323,
      "provides detailed": 2324,
      "sometimes performed under": 2325,
      "sent to": 2326,
      "less accurate than": 2327,
      "reduced by": 2328,
      "may reveal": 2329,
      "surgical technique": 2330,
      "performed first successful": 2331,
      "associated with": 2332,
      "preparation": 2333,
      "investigates": 2334,
      "freezes": 2335,
      "rehabilitation": 2336,
      "interacts with": 2337,
      "employs": 2338,
      "follow": 2339,
      "commonly used in": 2340,
      "can progress to": 2341,
      "repaired with": 2342,
      "technique includes": 2343,
      "variant of": 2344,
      "cost covered by": 2345,
      "prone to": 2346,
      "improved with": 2347,
      "applies": 2348,
      "modulated by": 2349,
      "concerning after": 2350,
      "assessed by": 2351,
      "is irreversible": 2352,
      "portable in": 2353,
      "alerts for": 2354,
      "urgent in": 2355,
      "may have": 2356,
      "appears as": 2357,
      "expert in": 2358,
      "attended by": 2359,
      "examines": 2360,
      "commonly found in": 2361,
      "screened for": 2362,
      "commonly require": 2363,
      "inserted via": 2364,
      "initiates": 2365,
      "vaporizes": 2366,
      "differentiates from": 2367,
      "uses external": 2368,
      "connects": 2369,
      "diagnose": 2370,
      "occurs in": 2371,
      "monitored via": 2372,
      "is common in": 2373,
      "weakened by": 2374,
      "assists in": 2375,
      "combated by": 2376,
      "resolves with": 2377,
      "provides anatomical context for": 2378,
      "innervates": 2379,
      "higher risk for": 2380,
      "can be": 2381,
      "prevalence tracked in": 2382,
      "may cause": 2383,
      "outcome": 2384,
      "implanted via": 2385,
      "\u7981\u5fcc\u4e8e": 2386,
      "anchor": 2387,
      "is more expensive": 2388,
      "associate with": 2389,
      "disrupts": 2390,
      "prioritize": 2391,
      "regulate": 2392,
      "consumes": 2393,
      "is a common": 2394,
      "hazardous": 2395,
      "repairs": 2396,
      "delay": 2397,
      "observes": 2398,
      "manage": 2399,
      "sterilizes": 2400,
      "compared to": 2401,
      "considered in": 2402,
      "pain management": 2403,
      "anatomy": 2404,
      "outcomes affect": 2405,
      "similar to": 2406,
      "bedside insertion requires": 2407,
      "modified for": 2408,
      "dependent on": 2409,
      "improves accuracy of": 2410,
      "documentation": 2411,
      "prescribes": 2412,
      "cannot reach": 2413,
      "inspects": 2414,
      "often need": 2415,
      "complicated by": 2416,
      "analyzed with": 2417,
      "treated by": 2418,
      "instrumentation": 2419,
      "contraindication for": 2420,
      "synonym of": 2421,
      "shows cold spot in": 2422,
      "insulated by": 2423,
      "incidental findings": 2424,
      "can reduce": 2425,
      "predicted by": 2426,
      "may obscure": 2427,
      "challenges": 2428,
      "sometimes performed with": 2429,
      "effects": 2430,
      "is vital for": 2431,
      "confounded by": 2432,
      "implants in": 2433,
      "offer": 2434,
      "duration varies": 2435,
      "analyzed for": 2436,
      "helps exclude": 2437,
      "has recovery period": 2438,
      "synthesizes": 2439,
      "evolve with": 2440,
      "postoperative follow-up": 2441,
      "kill": 2442,
      "has rate": 2443,
      "cautiously in": 2444,
      "medical indications include": 2445,
      "checks for": 2446,
      "optimized with": 2447,
      "potential source of": 2448,
      "compresses": 2449,
      "\u901a\u5e38\u5728": 2450,
      "emergency treated with": 2451,
      "consider": 2452,
      "extends": 2453,
      "disrupted by": 2454,
      "affects": 2455,
      "has complication": 2456,
      "newer than": 2457,
      "long-term risk": 2458,
      "no-scalpel technique reduces": 2459,
      "alternative for": 2460,
      "injected via": 2461,
      "are caused by": 2462,
      "may trigger": 2463
}